{
  "name": "wechat-article-writing-master",
  "industry": "WeChat Official Account article writing — 微信公众号「文章」这个 artifact 的写作、生产、分发、变现 (单篇文章为单位的 craft + ops + 商业化, 不含 SCRM / 私聊 / 群运营 / 朋友圈 SOP — 那些归 private-domain-ops)",
  "industry_cn": "公众号写作助手 (微信公众号文章 全链路 — 选题 / 标题 / 开篇 / 结构 / 行文 / 排版 / 配图 / 推送 / 涨粉 / 留言 / 二次传播 / 变现, 单 artifact = 一篇公众号推文)",
  "triggers": [
    "公众号",
    "公众号写作",
    "公众号运营",
    "微信公众号",
    "服务号",
    "订阅号",
    "10万+",
    "10w+",
    "推文",
    "头条",
    "次条",
    "三条",
    "次次条",
    "选题",
    "起标题",
    "标题党",
    "开篇",
    "金句",
    "排版",
    "135 编辑器",
    "秀米",
    "壹伴",
    "流量主",
    "互选广告",
    "广告位",
    "广点通",
    "新榜",
    "飞瓜数据",
    "西瓜数据",
    "知微数据",
    "微信指数",
    "看一看",
    "推荐流",
    "在看",
    "留言",
    "赞赏",
    "原创标",
    "白名单转载",
    "矩阵号",
    "视频号联动",
    "公众号变现",
    "公众号涨粉",
    "AI 写公众号",
    "自媒体写作"
  ],
  "locale": "zh-CN",
  "profile": "practitioner",
  "focus": {
    "primary": "operational",
    "secondary": "business"
  },
  "last_research_date": "2026-05-16",
  "source_count": 238,
  "primary_source_ratio": 0.4412,
  "tracks_covered": [
    "figures",
    "tools",
    "workflows",
    "canon",
    "sources",
    "glossary"
  ],
  "mental_models_count": 5,
  "playbook_rules_count": 8,
  "research_dimensions_count": 5,
  "sub_skills": [],
  "generator": "master-skill v1.3",
  "version": "1.3",
  "changelog": [
    {
      "version": "1.3",
      "date": "2026-05-16",
      "what": "Initial generation"
    }
  ]
}
